MacPackageTest/__init__.py
MacPackageTest/main.py
MacPackageTest2/__init__.py
MacPackageTest2/main.py
MacPackageTest2-0.1.dist-info/DESCRIPTION.rst
MacPackageTest2-0.1.dist-info/METADATA
MacPackageTest2-0.1.dist-info/RECORD
MacPackageTest2-0.1.dist-info/WHEEL
MacPackageTest2-0.1.dist-info/metadata.json
MacPackageTest2-0.1.dist-info/top_level.txt
Package_Test/__init__.py
Package_Test/main.py
