Metadata-Version: 2.0
Name: MacPackageTest2
Version: 0.1
Summary: MacPackageTest2
Home-page: UNKNOWN
Author: UNKNOWN
Author-email: UNKNOWN
License: UNKNOWN
Platform: UNKNOWN
